{
  "Ad_Priority" : "1",
  "Custom_Ad_Download_link" : [ "com.zgg.robot.transformation.game", 
                               "com.zgg.robot.transformation.game", 
                               "com.zgg.robot.transformation.game",
                               "com.zgg.robot.transformation.game",
                               "com.zgg.robot.transformation.game"
                              ],
      "Custom_Icon_Ad_Download_link" : [ "com.zgg.robot.transformation.game", 
                               "com.zgg.robot.transformation.game", 
                               "com.zgg.robot.transformation.game",
                               "com.zgg.robot.transformation.game",
                               "com.zgg.robot.transformation.game"
                              ],
  "Custom_Ad_Icons_URL" : [ "https://play-lh.googleusercontent.com/SvtzoMfUxHviR1lT-QNjEm64mnmM_jAPrOQdAWnehj25esZveL_3zsewEGAMh1TLcm0=w256-h256", 
                           "https://play-lh.googleusercontent.com/HkPi_-Jx3e46Kn4pHVgVUgSjQVNTR_NpxQF4bNhmBzDCkI-K1IHdLW2Jmh64PQJCh4sS=w256-h256", 
                           "https://play-lh.googleusercontent.com/k_1VmPu421cvrIMEK1WMpEP45DxFL425HVUJ0ft3Zkt-VmRPP-jrG8dnxy4dFZ0xYJ0=w256-h256",
                          "https://play-lh.googleusercontent.com/1maNZbwGOG22G77NwWzsoNGlWlACfNEwiS3t77N1V_IIWnFg6HnDvNbTqY0Fir9PozFQ=w256-h256",
                           "https://play-lh.googleusercontent.com/tgd2m9-21TYwMMTqop38siX3Yo9JMu5m-oKjEfBgkGpRXejBZkmYPdWqC1SYk4drsCE=w256-h256"
                          ],
  
  "Custom_Ad_ScreenShots_URL" : [ "https://play-lh.googleusercontent.com/HPJiXHKbne2k7J0bntpCl2Jm-oueZaSzId8pu83uaOESHuFffRKLgbhfxXBIaGKZpS_W=w1280-h720", 
                                 "https://play-lh.googleusercontent.com/Zg83pYIYSDwbP6gLFHoAXz21_nRmCrLLsXhnM_Z7ejGVygJHGifhe8MNKqPpqXTrFBsN=w1280-h720", 
                                 "https://play-lh.googleusercontent.com/D6RhTkMPbpY6eF5HstGGriK3if_HFO8psJ4TUaEiE3y5t7LldTjHpLvYAjQ1D5Fa_8c=w1280-h720" ,
                                "https://play-lh.googleusercontent.com/5iRaN4XQZeXLVVgnbSojFJT3CIVMyrBSGZr-wcgIqVnW3oq5s5LVjU6dZ6OkErgGXw=w1280-h720",
                                "https://play-lh.googleusercontent.com/kqH-VdgP2pr0dpd2Oaxt7-RzJXLF7cmFz5Tj_tfMaQ7P6drjpWr7ApRguAnjNxoYGZQ=w1280-h720"
                                ],
  "Indetifier_ID" : "com.Game.io.4x4.OFFRoad.JeepParking.2020",
  "Start_Showing_Ads" : true,
  "Hide_Ads" : false,
  "CutSceneLink" : "https://drive.google.com/u/0/uc?id=1Ixr0jilnxHGfEVLyHQrjJSqGAfUtudV2&export=download"
}
